{
  "NonSecs": {
    "ParamsVid": [ "101", "201", "301", "401", "501" ],
    "VidDict": {
      "1": "Clock",
      "14": "MDLN",
      "15": "SOFTREV",
      "50": "USER ID",
      "51": "Product ID",
      "100": "OP10 ControlState",
      "101": "OP10 Status",
      "102": "OP10 PreviousProcessState",
      "103": "OP10 REELID",
      "104": "OP10 WorkID",
      "105": "OP10 Query QTY",
      "106": "OP10 Count QTY",
      "107": "OP10 Number of input",
      "108": "OP10 Number of defects",
      "200": "OP20 ControlState",
      "201": "OP20 Status",
      "202": "OP20 PreviousProcessState",
      "203": "OP20 REELID",
      "204": "OP20 WorkID",
      "205": "OP20 Query QTY",
      "206": "OP20 Count QTY",
      "207": "OP20 Number of input",
      "208": "OP20 Number of defects",
      "300": "OP30 ControlState",
      "301": "OP30 Status",
      "302": "OP30 PreviousProcessState",
      "303": "OP30 REELID",
      "304": "OP30 WorkID",
      "305": "OP30 Query QTY",
      "306": "OP30 Count QTY",
      "307": "OP30 Number of input",
      "308": "OP30 Number of defects",
      "400": "OP40 ControlState",
      "401": "OP40 Status",
      "402": "OP40 PreviousProcessState",
      "403": "OP40 REELID",
      "404": "OP40 WorkID",
      "405": "OP40 Query QTY",
      "406": "OP40 Count QTY",
      "407": "OP40 Number of input",
      "408": "OP40 Number of defects",
      "500": "OP50 ControlState",
      "501": "OP50 Status",
      "502": "OP50 PreviousProcessState",
      "503": "OP50 REELID",
      "504": "OP50 WorkID",
      "505": "OP50 Query QTY",
      "506": "OP50 Count QTY",
      "507": "OP50 Number of input",
      "508": "OP50 Number of defects"
    },
    "SubEquipment": {
      "1": "EQPPR00010",
      "2": "EQCAS00001",
      "3": "EQPRE00030",
      "4": "EQCIS00002",
      "5": "EQPPR00011"
    },
    "ProcessStateCodes": {
      "IDLE": "Idle",
      "TEST": "Idle",
      "RUN": "Run",
      "ALARM": "Alarm",
      "INIT": "Idle"
    }
  },
  "Others": {

  }
}